linestickerdl/__init__.py
linestickerdl/cli.py
linestickerdl/downloader.py
line_sticker_dl-1.1.0.dist-info/entry_points.txt
line_sticker_dl-1.1.0.dist-info/WHEEL
line_sticker_dl-1.1.0.dist-info/METADATA
line_sticker_dl-1.1.0.dist-info/RECORD
