Metadata-Version: 2.1
Name: line-sticker-dl
Version: 1.1.0
Summary: line sticker downloader
Home-page: https://github.com/granitosaurus/line-sticker-dl
License: GPL-3.0-or-later
Keywords: scraper,web-crawling,cli,sticker
Author: granitosaurus
Author-email: tinarg@protonmail.com
Requires-Python: >=3.8,<4.0
Classifier: License :: OSI Approved :: GNU General Public License v3 or later (GPLv3+)
Classifier: Programming Language :: Python :: 3
Classifier: Programming Language :: Python :: 3.8
Requires-Dist: aiohttp (>=3.6.2,<4.0.0)
Requires-Dist: click (>=7.1.1,<8.0.0)
Requires-Dist: parsel (>=1.5.2,<2.0.0)
Requires-Dist: questionary (>=1.5.1,<2.0.0)
Project-URL: Repository, https://github.com/granitosaurus/line-sticker-dl
